hexpy/__init__.py
hexpy/activity.py
hexpy/analysis.py
hexpy/base.py
hexpy/content_upload.py
hexpy/custom.py
hexpy/head.html
hexpy/hexpy.py
hexpy/metadata.py
hexpy/models.py
hexpy/monitor.py
hexpy/project.py
hexpy/py.typed
hexpy/realtime.py
hexpy/session.py
hexpy/streams.py
hexpy-0.7.3.dist-info/LICENSE
hexpy-0.7.3.dist-info/METADATA
hexpy-0.7.3.dist-info/WHEEL
hexpy-0.7.3.dist-info/entry_points.txt
hexpy-0.7.3.dist-info/top_level.txt
hexpy-0.7.3.dist-info/RECORD
