Metadata-Version: 2.1
Name: hexpy
Version: 0.7.3
Summary: Python Client for Crimson Hexagon API
Home-page: https://sullivancolin.github.io/hexpy/
Author: Colin Sullivan
Author-email: csullivan@crimsonhexagon.com
License: UNKNOWN
Keywords: hexpy
Platform: UNKNOWN
Classifier: Development Status :: 2 - Pre-Alpha
Classifier: Intended Audience :: Developers
Classifier: Natural Language :: English
Classifier: Programming Language :: Python :: 3.6
Classifier: Programming Language :: Python :: 3.7
Classifier: Programming Language :: Python :: 3.8
Requires-Python: >=3.6
Requires-Dist: xlrd (>=1.1.0)
Requires-Dist: requests (>=2.22.0)
Requires-Dist: click (>=7.0)
Requires-Dist: click-help-colors (>=0.5)
Requires-Dist: pandas (>=0.20.3)
Requires-Dist: openpyxl (>=2.4.8)
Requires-Dist: pendulum (>=1.3.2)
Requires-Dist: pydantic (>=1.1)
Requires-Dist: ftfy (>=5.5.1)
